CHANGELOG.md
LICENSE.md
README.md
TODO.md
example.png
setup.py
examples/expertsolver_example.py
examples/lapackdrivers_example.py
examples/sudoku_lhs.py
examples/wlsqm_example.py
wlsqm/__init__.py
wlsqm.egg-info/PKG-INFO
wlsqm.egg-info/SOURCES.txt
wlsqm.egg-info/dependency_links.txt
wlsqm.egg-info/not-zip-safe
wlsqm.egg-info/requires.txt
wlsqm.egg-info/top_level.txt
wlsqm/fitter/__init__.py
wlsqm/fitter/defs.c
wlsqm/fitter/defs.pxd
wlsqm/fitter/defs.pyx
wlsqm/fitter/expert.c
wlsqm/fitter/expert.pyx
wlsqm/fitter/impl.c
wlsqm/fitter/impl.pxd
wlsqm/fitter/impl.pyx
wlsqm/fitter/infra.c
wlsqm/fitter/infra.pxd
wlsqm/fitter/infra.pyx
wlsqm/fitter/interp.c
wlsqm/fitter/interp.pxd
wlsqm/fitter/interp.pyx
wlsqm/fitter/polyeval.c
wlsqm/fitter/polyeval.pxd
wlsqm/fitter/polyeval.pyx
wlsqm/fitter/simple.c
wlsqm/fitter/simple.pxd
wlsqm/fitter/simple.pyx
wlsqm/utils/__init__.py
wlsqm/utils/lapackdrivers.c
wlsqm/utils/lapackdrivers.pxd
wlsqm/utils/lapackdrivers.pyx
wlsqm/utils/ptrwrap.c
wlsqm/utils/ptrwrap.pxd
wlsqm/utils/ptrwrap.pyx