Metadata-Version: 1.1
Name: wlsqm
Version: 0.1.6
Summary: Weighted least squares meshless interpolator
Home-page: https://github.com/Technologicat/python-wlsqm
Author: Juha Jeronen
Author-email: juha.jeronen@jyu.fi
License: BSD
Keywords: numerical interpolation differentiation curve-fitting least-squares meshless numpy cython
Platform: Linux
Classifier: Development Status :: 4 - Beta
Classifier: Environment :: Console
Classifier: Intended Audience :: Developers
Classifier: Intended Audience :: Science/Research
Classifier: License :: OSI Approved :: BSD License
Classifier: Operating System :: POSIX :: Linux
Classifier: Programming Language :: Cython
Classifier: Programming Language :: Python
Classifier: Programming Language :: Python :: 2
Classifier: Programming Language :: Python :: 2.7
Classifier: Programming Language :: Python :: 3
Classifier: Programming Language :: Python :: 3.4
Classifier: Topic :: Scientific/Engineering
Classifier: Topic :: Scientific/Engineering :: Mathematics
Classifier: Topic :: Software Development :: Libraries
Classifier: Topic :: Software Development :: Libraries :: Python Modules
Provides: wlsqm
